LICENSE
MANIFEST.in
README.rst
setup.py
django_rest_sessions.egg-info/PKG-INFO
django_rest_sessions.egg-info/SOURCES.txt
django_rest_sessions.egg-info/dependency_links.txt
django_rest_sessions.egg-info/not-zip-safe
django_rest_sessions.egg-info/requires.txt
django_rest_sessions.egg-info/top_level.txt
rest_sessions/__init__.py
rest_sessions/mock.py
rest_sessions/session.py