Metadata-Version: 1.1
Name: django-rest-sessions
Version: 0.2.2
Summary: Rest Session Backend For Django
Home-page: https://stash.temposoftware.com/projects/TMC/repos/django-rest-sessions/browse
Author: Hodur Sigurdor Heidarsson
Author-email: hodur@temposoftware.com
License: MIT
Keywords: django,sessions,
Platform: UNKNOWN
Classifier: Programming Language :: Python :: 3
Classifier: Topic :: Software Development :: Libraries :: Python Modules
Classifier: Intended Audience :: Developers
Classifier: Framework :: Django
Classifier: Environment :: Web Environment
